rede/__init__.py
rede/api.py
rede/exceptions.py
rede_api-0.0.8.dist-info/LICENSE
rede_api-0.0.8.dist-info/METADATA
rede_api-0.0.8.dist-info/WHEEL
rede_api-0.0.8.dist-info/top_level.txt
rede_api-0.0.8.dist-info/RECORD
