Metadata-Version: 2.1
Name: rede-api
Version: 0.0.8
Summary: A package to handle rede API
Home-page: https://github.com/darleisantossoares/rede_api
Author: Darlei Soares
Author-email: darleisantossoares@gmail.com
License: MIT
Platform: UNKNOWN
Classifier: Programming Language :: Python :: 3
Classifier: License :: OSI Approved :: MIT License
Classifier: Operating System :: OS Independent
Requires-Dist: requests
